autocog/__init__.py
autocog/ai.py
autocog/autocog.py
autocog/prompts.py
autocog/retry.py
autocog/testdata.py
autocog/prompts/cog_predict.tpl
autocog/prompts/cog_python_docs.tpl
autocog/prompts/cog_yaml_docs.tpl
autocog/prompts/diagnose_error.tpl
autocog/prompts/fix_cog_yaml.tpl
autocog/prompts/fix_predict_py.tpl
autocog/prompts/generate_initial.tpl
autocog/prompts/get_packages.tpl
autocog/prompts/order_paths.tpl
autocog/prompts/package_error.tpl
autocog/prompts/system.tpl
autocog-0.0.11.dist-info/METADATA
autocog-0.0.11.dist-info/WHEEL
autocog-0.0.11.dist-info/entry_points.txt
autocog-0.0.11.dist-info/top_level.txt
autocog-0.0.11.dist-info/RECORD
