Metadata-Version: 2.1
Name: autocog
Version: 0.0.11
Home-page: https://github.com/andreasjansson/AutoCog
Requires-Dist: openai
Requires-Dist: click
Requires-Dist: Pillow
Requires-Dist: pydub
Requires-Dist: opencv-python
Requires-Dist: anthropic
Requires-Dist: jinja2
Requires-Dist: pypi-simple
